turon/__init__.py
turon/exceptions.py
turon/session.py
turon-1.0.0.dist-info/LICENSE.rst
turon-1.0.0.dist-info/METADATA
turon-1.0.0.dist-info/WHEEL
turon-1.0.0.dist-info/top_level.txt
turon-1.0.0.dist-info/RECORD
