Metadata-Version: 2.1
Name: turon
Version: 1.0.0
Summary: Python adapter for turon.io
Home-page: https://ww.github.com/tryturon/turon-py
Author: Scott Cruwys
Author-email: scott@turon.io
Platform: any
Requires-Python: ==3.8.*
License-File: LICENSE.rst
Requires-Dist: pandas <3,>2
Requires-Dist: requests <3,>2
